geezlibs/__init__.py
geezlibs/client.py
geezlibs/dispatcher.py
geezlibs/emoji.py
geezlibs/file_id.py
geezlibs/filters.py
geezlibs/mime_types.py
geezlibs/sync.py
geezlibs/utils.py
geezlibs/connection/__init__.py
geezlibs/connection/connection.py
geezlibs/connection/transport/__init__.py
geezlibs/connection/transport/tcp/__init__.py
geezlibs/connection/transport/tcp/tcp.py
geezlibs/connection/transport/tcp/tcp_abridged.py
geezlibs/connection/transport/tcp/tcp_abridged_o.py
geezlibs/connection/transport/tcp/tcp_full.py
geezlibs/connection/transport/tcp/tcp_intermediate.py
geezlibs/connection/transport/tcp/tcp_intermediate_o.py
geezlibs/crypto/__init__.py
geezlibs/crypto/aes.py
geezlibs/crypto/mtproto.py
geezlibs/crypto/prime.py
geezlibs/crypto/rsa.py
geezlibs/enums/__init__.py
geezlibs/enums/auto_name.py
geezlibs/enums/chat_action.py
geezlibs/enums/chat_event_action.py
geezlibs/enums/chat_member_status.py
geezlibs/enums/chat_members_filter.py
geezlibs/enums/chat_type.py
geezlibs/enums/message_entity_type.py
geezlibs/enums/message_media_type.py
geezlibs/enums/message_service_type.py
geezlibs/enums/messages_filter.py
geezlibs/enums/msg_types.py
geezlibs/enums/next_code_type.py
geezlibs/enums/parse_mode.py
geezlibs/enums/poll_type.py
geezlibs/enums/sent_code_type.py
geezlibs/enums/user_status.py
geezlibs/errors/__init__.py
geezlibs/errors/rpc_error.py
geezlibs/geez/__init__.py
geezlibs/geez/database/__init__.py
geezlibs/geez/database/gbandb.py
geezlibs/geez/database/gmutedb.py
geezlibs/geez/database/pmpermitdb.py
geezlibs/geez/database/rraid.py
geezlibs/geez/helper/PyroHelpers.py
geezlibs/geez/helper/__init__.py
geezlibs/geez/helper/adminHelpers.py
geezlibs/geez/helper/aiohttp_helper.py
geezlibs/geez/helper/basic.py
geezlibs/geez/helper/constants.py
geezlibs/geez/helper/data.py
geezlibs/geez/helper/inline.py
geezlibs/geez/helper/interval.py
geezlibs/geez/helper/parser.py
geezlibs/geez/helper/utility.py
geezlibs/geez/utils/__init__.py
geezlibs/geez/utils/misc.py
geezlibs1-2.0.0.dist-info/LICENSE
geezlibs1-2.0.0.dist-info/METADATA
geezlibs1-2.0.0.dist-info/NOTICE
geezlibs1-2.0.0.dist-info/WHEEL
geezlibs1-2.0.0.dist-info/top_level.txt
geezlibs1-2.0.0.dist-info/RECORD
